paftacular/__init__.py
paftacular/annotation.py
paftacular/constants.py
paftacular/parser.py
paftacular/py.typed
paftacular/util.py
paftacular/comps/__init__.py
paftacular/comps/base.py
paftacular/comps/ions.py
paftacular/comps/modifiers.py
paftacular/comps/util.py
paftacular-0.1.0.dist-info/METADATA
paftacular-0.1.0.dist-info/WHEEL
paftacular-0.1.0.dist-info/licenses/LICENSE
paftacular-0.1.0.dist-info/RECORD
