Metadata-Version: 2.4
Name: paftacular
Version: 0.1.0
Summary: mzpaf parser
Author-email: Patrick Garrett <pgarrett@scripps.edu>
Maintainer-email: Patrick Garrett <pgarrett@scripps.edu>
License-File: LICENSE
Classifier: Development Status :: 4 - Beta
Classifier: Intended Audience :: Science/Research
Classifier: Operating System :: OS Independent
Classifier: Programming Language :: Python :: 3
Classifier: Programming Language :: Python :: 3.12
Classifier: Topic :: Scientific/Engineering :: Bio-Informatics
Classifier: Topic :: Scientific/Engineering :: Chemistry
Classifier: Typing :: Typed
Requires-Python: >=3.12
Requires-Dist: tacular>=1.0.0
Provides-Extra: all
Requires-Dist: peptacular>=2.5.0; extra == 'all'
Requires-Dist: pysmiles>=2.0.1; extra == 'all'
Provides-Extra: sequence
Requires-Dist: peptacular>=2.5.0; extra == 'sequence'
Provides-Extra: smiles
Requires-Dist: pysmiles>=2.0.1; extra == 'smiles'
